astroimages_fits/__init__.py
astroimages_fits/fits_test_util_functions.py
astroimages_fits/fits_util_functions.py
astroimages_fits-0.2.4.dist-info/LICENSE
astroimages_fits-0.2.4.dist-info/METADATA
astroimages_fits-0.2.4.dist-info/WHEEL
astroimages_fits-0.2.4.dist-info/top_level.txt
astroimages_fits-0.2.4.dist-info/RECORD
