Metadata-Version: 2.1
Name: astroimages-fits
Version: 0.2.4
Summary: FITS files related routines and classes
Home-page: https://github.com/AstroImages/astroimages-fits
Author: Rodrigo de Souza
Author-email: rsouza01@gmail.com
License: MIT License
Requires-Dist: astropy
Requires-Dist: numpy
